{
  "db_name": "PostgreSQL",
  "query": "SELECT * FROM \"todo\" ORDER BY \"timestamp\" ASC, \"id\" DESC LIMIT $1",
  "describe": {
    "columns": [
      {
        "ordinal": 0,
        "name": "id",
        "type_info": "Int4"
      },
      {
        "ordinal": 1,
        "name": "timestamp",
        "type_info": "Timestamp"
      },
      {
        "ordinal": 2,
        "name": "item",
        "type_info": "Varchar"
      }
    ],
    "parameters": {
      "Left": [
        "Int8"
      ]
    },
    "nullable": [
      false,
      false,
      false
    ]
  },
  "hash": "10c79c182f2e7a6fac7a1a0a99d75f185429b8b6cfd806334635d612f7bf9229"
}
